langwatch/__init__.py
langwatch/__version__.py
langwatch/attributes.py
langwatch/batch_evaluation.py
langwatch/client.py
langwatch/evaluations.py
langwatch/guardrails.py
langwatch/langchain.py
langwatch/litellm.py
langwatch/login.py
langwatch/openai.py
langwatch/py.typed
langwatch/state.py
langwatch/tracer.py
langwatch/types.py
langwatch/dataset/__init__.py
langwatch/domain/__init__.py
langwatch/dspy/__init__.py
langwatch/evaluation/__init__.py
langwatch/experiment/__init__.py
langwatch/experiment/experiment.py
langwatch/experiment/platform_run.py
langwatch/exporters/filterable_batch_span_exporter.py
langwatch/generated/langwatch_rest_api_client/__init__.py
langwatch/generated/langwatch_rest_api_client/client.py
langwatch/generated/langwatch_rest_api_client/errors.py
langwatch/generated/langwatch_rest_api_client/py.typed
langwatch/generated/langwatch_rest_api_client/types.py
langwatch/generated/langwatch_rest_api_client/api/__init__.py
langwatch/generated/langwatch_rest_api_client/api/default/__init__.py
langwatch/generated/langwatch_rest_api_client/api/default/delete_api_annotations_id.py
langwatch/generated/langwatch_rest_api_client/api/default/delete_api_prompts_by_id.py
langwatch/generated/langwatch_rest_api_client/api/default/delete_api_scenario_events.py
langwatch/generated/langwatch_rest_api_client/api/default/get_api_annotations.py
langwatch/generated/langwatch_rest_api_client/api/default/get_api_annotations_id.py
langwatch/generated/langwatch_rest_api_client/api/default/get_api_annotations_trace_id.py
langwatch/generated/langwatch_rest_api_client/api/default/get_api_dataset_by_slug_or_id.py
langwatch/generated/langwatch_rest_api_client/api/default/get_api_prompts.py
langwatch/generated/langwatch_rest_api_client/api/default/get_api_prompts_by_id.py
langwatch/generated/langwatch_rest_api_client/api/default/get_api_prompts_by_id_versions.py
langwatch/generated/langwatch_rest_api_client/api/default/get_api_trace_id.py
langwatch-0.10.1.dist-info/METADATA
langwatch-0.10.1.dist-info/WHEEL
langwatch-0.10.1.dist-info/RECORD
